setup.py
yamlgen/__init__.py
yamlgen/__main__.py
yamlgen/genyaml.py
yamlgen/util.py
yamlgen.egg-info/PKG-INFO
yamlgen.egg-info/SOURCES.txt
yamlgen.egg-info/dependency_links.txt
yamlgen.egg-info/entry_points.txt
yamlgen.egg-info/requires.txt
yamlgen.egg-info/top_level.txt