Metadata-Version: 2.1
Name: yamlgen
Version: 1.0.1
Summary: A package to generate yaml file. Convert Json String to Yaml
Home-page: https://github.com/razaqK/yamlgen
Author: Razaq Kloc
Author-email: razaqkor@gmail.com
License: UNKNOWN
Platform: UNKNOWN
Classifier: Intended Audience :: Developers
Classifier: Programming Language :: Python :: 3.6
Classifier: License :: OSI Approved :: MIT License
Classifier: Operating System :: OS Independent
Requires-Python: >=3.6
